README.md
setup.py
kan_secret_storage/__init__.py
kan_secret_storage/main.py
kan_secret_storage.egg-info/PKG-INFO
kan_secret_storage.egg-info/SOURCES.txt
kan_secret_storage.egg-info/dependency_links.txt
kan_secret_storage.egg-info/requires.txt
kan_secret_storage.egg-info/top_level.txt