Metadata-Version: 2.1
Name: kan-secret-storage
Version: 0.2
Summary: Python Secret Storage package
Home-page: https://github.com/kansoftware/secret_storage
Author: Andrew KAN
Author-email: kan@kansoftware.ru
License: GPL-3
Platform: UNKNOWN
